<xml>
	<settings>
		<name>restricted_mode_warning</name>
	</settings>
	<layout>
		<element name="background"			type="Panel" 		box="0,0.15,1.0,0.7" 	  BackColor="0,0,0,220" AspectScaling="0" />		
		<element name="intro_label"		 	type="Label"		box="0.1,0.15,0.8,0.10"     ForeColor="200,200,200,220" HAlign="Center" VAlign="ScaleToFit" Padding="0,0,0,0" Value="#restricted_mode_warning_title" UseMarkup="true" />
		<element name="description_label"	type="Label"		box="0.05,0.30,0.9,0.40"     ForeColor="200,200,200,220" HAlign="Center" VAlign="Center" Padding="0,0,0,0" Value="#restricted_mode_warning" UseMarkup="true" />
		<element name="back_button" 		type="Button" 		box="0.35,0.75,0.3,0.070"  FrameColor="255,255,255,200" Hotkey="GUI_Back" Value="#menu_confirm"  />	
	</layout>
</xml>